goodwiki/__init__.py
goodwiki/client.py
goodwiki/constants.py
goodwiki/errors.py
goodwiki/mwp_utils.py
goodwiki/tags.py
goodwiki/utils.py
goodwiki-1.0.1.dist-info/LICENSE
goodwiki-1.0.1.dist-info/WHEEL
goodwiki-1.0.1.dist-info/METADATA
goodwiki-1.0.1.dist-info/RECORD
