Metadata-Version: 2.1
Name: goodwiki
Version: 1.0.1
Summary: Utility that converts Wikipedia pages into GitHub-flavored Markdown.
Home-page: https://github.com/euirim/goodwiki
License: MIT
Keywords: wikipedia,markdown,dataset,wikitext,wikicode
Author: Euirim Choi
Author-email: euirim@gmail.com
Requires-Python: >=3.11,<4.0
Classifier: License :: OSI Approved :: MIT License
Classifier: Programming Language :: Python :: 3
Classifier: Programming Language :: Python :: 3.11
Classifier: Topic :: Text Processing
Classifier: Topic :: Text Processing :: Filters
Classifier: Topic :: Text Processing :: Markup :: Markdown
Requires-Dist: click (>=8.1.6,<9.0.0)
Requires-Dist: httpx (>=0.24.1,<0.25.0)
Requires-Dist: multiprocess (>=0.70.15,<0.71.0)
Requires-Dist: mwparserfromhell (>=0.6.4,<0.7.0)
Requires-Dist: pyarrow (>=12.0.1,<13.0.0)
Requires-Dist: pypandoc (>=1.11,<2.0)
Requires-Dist: tqdm (>=4.66.1,<5.0.0)
Requires-Dist: wikipedia-api (>=0.6.0,<0.7.0)
Project-URL: Repository, https://github.com/euirim/goodwiki
